<?xml version='1.0' encoding='UTF-8' standalone='yes' ?>
<hierarchy rotation="0">
    <node index="0" text="" resource-id="" class="android.widget.FrameLayout" package="com.android.settings"
          content-desc="" checkable="false" checked="false" clickable="false" enabled="true" focusable="false"
          focused="false" scrollable="false" long-clickable="false" password="false" selected="false"
          bounds="[0,0][1080,1776]">
        <node index="0" text="" resource-id="" class="android.widget.LinearLayout" package="com.android.settings"
              content-desc="" checkable="false" checked="false" clickable="false" enabled="true" focusable="false"
              focused="false" scrollable="false" long-clickable="false" password="false" selected="false"
              bounds="[0,0][1080,1776]">
            <node index="0" text="" resource-id="android:id/content" class="android.widget.FrameLayout"
                  package="com.android.settings" content-desc="" checkable="false" checked="false" clickable="false"
                  enabled="true" focusable="false" focused="false" scrollable="false" long-clickable="false"
                  password="false" selected="false" bounds="[0,72][1080,1776]">
                <node index="0" text="" resource-id="com.android.settings:id/drawer_layout"
                      class="android.support.v4.widget.DrawerLayout" package="com.android.settings" content-desc=""
                      checkable="false" checked="false" clickable="false" enabled="true" focusable="false"
                      focused="false" scrollable="false" long-clickable="false" password="false" selected="false"
                      bounds="[0,72][1080,1776]">
                    <node index="0" text="" resource-id="com.android.settings:id/content_parent"
                          class="android.widget.LinearLayout" package="com.android.settings" content-desc=""
                          checkable="false" checked="false" clickable="false" enabled="true" focusable="false"
                          focused="false" scrollable="false" long-clickable="false" password="false" selected="false"
                          bounds="[0,72][1080,1776]">
                        <node index="0" text="" resource-id="com.android.settings:id/action_bar"
                              class="android.view.ViewGroup" package="com.android.settings" content-desc=""
                              checkable="false" checked="false" clickable="false" enabled="true" focusable="false"
                              focused="false" scrollable="false" long-clickable="false" password="false"
                              selected="false" bounds="[0,72][1080,240]">
                            <node index="0" text="Network &amp; Internet" resource-id="" class="android.widget.TextView"
                                  package="com.android.settings" content-desc="" checkable="false" checked="false"
                                  clickable="false" enabled="true" focusable="false" focused="false" scrollable="false"
                                  long-clickable="false" password="false" selected="false" bounds="[48,115][550,196]"/>
                            <node index="1" text="" resource-id="" class="android.widget.LinearLayout"
                                  package="com.android.settings" content-desc="" checkable="false" checked="false"
                                  clickable="false" enabled="true" focusable="false" focused="false" scrollable="false"
                                  long-clickable="false" password="false" selected="false" bounds="[960,72][1080,240]">
                                <node index="0" text="" resource-id="" class="android.widget.ImageButton"
                                      package="com.android.settings" content-desc="More options" checkable="false"
                                      checked="false" clickable="true" enabled="true" focusable="true" focused="false"
                                      scrollable="false" long-clickable="true" password="false" selected="false"
                                      bounds="[960,84][1080,228]"/>
                            </node>
                        </node>
                        <node index="2" text="" resource-id="com.android.settings:id/content_frame"
                              class="android.widget.FrameLayout" package="com.android.settings" content-desc=""
                              checkable="false" checked="false" clickable="false" enabled="true" focusable="false"
                              focused="false" scrollable="false" long-clickable="false" password="false"
                              selected="false" bounds="[0,240][1080,1776]">
                            <node index="0" text="" resource-id="" class="android.widget.LinearLayout"
                                  package="com.android.settings" content-desc="" checkable="false" checked="false"
                                  clickable="false" enabled="true" focusable="false" focused="false" scrollable="false"
                                  long-clickable="false" password="false" selected="false" bounds="[0,240][1080,1776]">
                                <node index="0" text="" resource-id="" class="android.widget.LinearLayout"
                                      package="com.android.settings" content-desc="" checkable="false" checked="false"
                                      clickable="false" enabled="true" focusable="false" focused="false"
                                      scrollable="false" long-clickable="false" password="false" selected="false"
                                      bounds="[0,240][1080,1776]">
                                    <node index="0" text="" resource-id="com.android.settings:id/main_content"
                                          class="android.widget.FrameLayout" package="com.android.settings"
                                          content-desc="" checkable="false" checked="false" clickable="false"
                                          enabled="true" focusable="false" focused="false" scrollable="false"
                                          long-clickable="false" password="false" selected="false"
                                          bounds="[0,240][1080,1776]">
                                        <node index="0" text="" resource-id="com.android.settings:id/container_material"
                                              class="android.widget.LinearLayout" package="com.android.settings"
                                              content-desc="" checkable="false" checked="false" clickable="false"
                                              enabled="true" focusable="false" focused="false" scrollable="false"
                                              long-clickable="false" password="false" selected="false"
                                              bounds="[0,240][1080,1776]">
                                            <node index="0" text="" resource-id="android:id/list_container"
                                                  class="android.widget.FrameLayout" package="com.android.settings"
                                                  content-desc="" checkable="false" checked="false" clickable="false"
                                                  enabled="true" focusable="false" focused="false" scrollable="false"
                                                  long-clickable="false" password="false" selected="false"
                                                  bounds="[0,240][1080,1776]">
                                                <node index="0" text="" resource-id="com.android.settings:id/list"
                                                      class="android.support.v7.widget.RecyclerView"
                                                      package="com.android.settings" content-desc="" checkable="false"
                                                      checked="false" clickable="false" enabled="true" focusable="true"
                                                      focused="true" scrollable="false" long-clickable="false"
                                                      password="false" selected="false" bounds="[0,240][1080,1776]">
                                                    <node index="0" text="" resource-id=""
                                                          class="android.widget.LinearLayout"
                                                          package="com.android.settings" content-desc=""
                                                          checkable="false" checked="false" clickable="true"
                                                          enabled="true" focusable="true" focused="false"
                                                          scrollable="false" long-clickable="false" password="false"
                                                          selected="false" bounds="[0,240][1080,458]">
                                                        <node index="0" text="" resource-id=""
                                                              class="android.widget.LinearLayout"
                                                              package="com.android.settings" content-desc=""
                                                              checkable="false" checked="false" clickable="false"
                                                              enabled="true" focusable="false" focused="false"
                                                              scrollable="false" long-clickable="false" password="false"
                                                              selected="false" bounds="[0,240][841,458]">
                                                            <node index="0" text=""
                                                                  resource-id="com.android.settings:id/icon_frame"
                                                                  class="android.widget.LinearLayout"
                                                                  package="com.android.settings" content-desc=""
                                                                  checkable="false" checked="false" clickable="false"
                                                                  enabled="true" focusable="false" focused="false"
                                                                  scrollable="false" long-clickable="false"
                                                                  password="false" selected="false"
                                                                  bounds="[36,301][216,397]">
                                                                <node index="0" text="" resource-id="android:id/icon"
                                                                      class="android.widget.ImageView"
                                                                      package="com.android.settings" content-desc=""
                                                                      checkable="false" checked="false"
                                                                      clickable="false" enabled="true" focusable="false"
                                                                      focused="false" scrollable="false"
                                                                      long-clickable="false" password="false"
                                                                      selected="false" bounds="[36,313][108,385]"/>
                                                            </node>
                                                            <node index="1" text="" resource-id=""
                                                                  class="android.widget.RelativeLayout"
                                                                  package="com.android.settings" content-desc=""
                                                                  checkable="false" checked="false" clickable="false"
                                                                  enabled="true" focusable="false" focused="false"
                                                                  scrollable="false" long-clickable="false"
                                                                  password="false" selected="false"
                                                                  bounds="[216,240][793,458]">
                                                                <node index="0" text="Wi‑Fi"
                                                                      resource-id="android:id/title"
                                                                      class="android.widget.TextView"
                                                                      package="com.android.settings" content-desc=""
                                                                      checkable="false" checked="false"
                                                                      clickable="false" enabled="true" focusable="false"
                                                                      focused="false" scrollable="false"
                                                                      long-clickable="false" password="false"
                                                                      selected="false" bounds="[216,288][323,353]"/>
                                                                <node index="1" text="Not connected"
                                                                      resource-id="android:id/summary"
                                                                      class="android.widget.TextView"
                                                                      package="com.android.settings" content-desc=""
                                                                      checkable="false" checked="false"
                                                                      clickable="false" enabled="true" focusable="false"
                                                                      focused="false" scrollable="false"
                                                                      long-clickable="false" password="false"
                                                                      selected="false" bounds="[216,353][490,410]"/>
                                                            </node>
                                                        </node>
                                                        <node index="1" text=""
                                                              resource-id="com.android.settings:id/two_target_divider"
                                                              class="android.widget.LinearLayout"
                                                              package="com.android.settings" content-desc=""
                                                              checkable="false" checked="false" clickable="false"
                                                              enabled="true" focusable="false" focused="false"
                                                              scrollable="false" long-clickable="false" password="false"
                                                              selected="false" bounds="[841,240][844,458]">
                                                            <node index="0" text="" resource-id=""
                                                                  class="android.view.View"
                                                                  package="com.android.settings" content-desc=""
                                                                  checkable="false" checked="false" clickable="false"
                                                                  enabled="true" focusable="false" focused="false"
                                                                  scrollable="false" long-clickable="false"
                                                                  password="false" selected="false"
                                                                  bounds="[841,288][844,410]"/>
                                                        </node>
                                                        <node index="2" text="" resource-id="android:id/widget_frame"
                                                              class="android.widget.LinearLayout"
                                                              package="com.android.settings" content-desc=""
                                                              checkable="false" checked="false" clickable="true"
                                                              enabled="true" focusable="true" focused="false"
                                                              scrollable="false" long-clickable="false" password="false"
                                                              selected="false" bounds="[844,240][1080,458]">
                                                            <node index="0" text="ON"
                                                                  resource-id="com.android.settings:id/switchWidget"
                                                                  class="android.widget.Switch"
                                                                  package="com.android.settings" content-desc="Wi‑Fi"
                                                                  checkable="true" checked="true" clickable="false"
                                                                  enabled="true" focusable="true" focused="false"
                                                                  scrollable="false" long-clickable="false"
                                                                  password="false" selected="false"
                                                                  bounds="[844,240][1080,458]"/>
                                                        </node>
                                                    </node>
                                                    <node index="1" text="" resource-id=""
                                                          class="android.widget.LinearLayout"
                                                          package="com.android.settings" content-desc=""
                                                          checkable="false" checked="false" clickable="true"
                                                          enabled="true" focusable="true" focused="false"
                                                          scrollable="false" long-clickable="false" password="false"
                                                          selected="false" bounds="[0,458][1080,676]">
                                                        <node index="0" text="" resource-id=""
                                                              class="android.widget.LinearLayout"
                                                              package="com.android.settings" content-desc=""
                                                              checkable="false" checked="false" clickable="false"
                                                              enabled="true" focusable="false" focused="false"
                                                              scrollable="false" long-clickable="false" password="false"
                                                              selected="false" bounds="[0,458][1080,676]">
                                                            <node index="0" text=""
                                                                  resource-id="com.android.settings:id/icon_frame"
                                                                  class="android.widget.LinearLayout"
                                                                  package="com.android.settings" content-desc=""
                                                                  checkable="false" checked="false" clickable="false"
                                                                  enabled="true" focusable="false" focused="false"
                                                                  scrollable="false" long-clickable="false"
                                                                  password="false" selected="false"
                                                                  bounds="[36,519][216,615]">
                                                                <node index="0" text="" resource-id="android:id/icon"
                                                                      class="android.widget.ImageView"
                                                                      package="com.android.settings" content-desc=""
                                                                      checkable="false" checked="false"
                                                                      clickable="false" enabled="true" focusable="false"
                                                                      focused="false" scrollable="false"
                                                                      long-clickable="false" password="false"
                                                                      selected="false" bounds="[36,531][108,603]"/>
                                                            </node>
                                                            <node index="1" text="" resource-id=""
                                                                  class="android.widget.RelativeLayout"
                                                                  package="com.android.settings" content-desc=""
                                                                  checkable="false" checked="false" clickable="false"
                                                                  enabled="true" focusable="false" focused="false"
                                                                  scrollable="false" long-clickable="false"
                                                                  password="false" selected="false"
                                                                  bounds="[216,458][1032,676]">
                                                                <node index="0" text="Mobile network"
                                                                      resource-id="android:id/title"
                                                                      class="android.widget.TextView"
                                                                      package="com.android.settings" content-desc=""
                                                                      checkable="false" checked="false"
                                                                      clickable="false" enabled="true" focusable="false"
                                                                      focused="false" scrollable="false"
                                                                      long-clickable="false" password="false"
                                                                      selected="false" bounds="[216,506][544,571]"/>
                                                                <node index="1" text="Android"
                                                                      resource-id="android:id/summary"
                                                                      class="android.widget.TextView"
                                                                      package="com.android.settings" content-desc=""
                                                                      checkable="false" checked="false"
                                                                      clickable="false" enabled="true" focusable="false"
                                                                      focused="false" scrollable="false"
                                                                      long-clickable="false" password="false"
                                                                      selected="false" bounds="[216,571][362,628]"/>
                                                            </node>
                                                        </node>
                                                    </node>
                                                    <node index="2" text="" resource-id=""
                                                          class="android.widget.LinearLayout"
                                                          package="com.android.settings" content-desc=""
                                                          checkable="false" checked="false" clickable="true"
                                                          enabled="true" focusable="true" focused="false"
                                                          scrollable="false" long-clickable="false" password="false"
                                                          selected="false" bounds="[0,676][1080,894]">
                                                        <node index="0" text=""
                                                              resource-id="com.android.settings:id/icon_frame"
                                                              class="android.widget.LinearLayout"
                                                              package="com.android.settings" content-desc=""
                                                              checkable="false" checked="false" clickable="false"
                                                              enabled="true" focusable="false" focused="false"
                                                              scrollable="false" long-clickable="false" password="false"
                                                              selected="false" bounds="[36,737][216,833]">
                                                            <node index="0" text="" resource-id="android:id/icon"
                                                                  class="android.widget.ImageView"
                                                                  package="com.android.settings" content-desc=""
                                                                  checkable="false" checked="false" clickable="false"
                                                                  enabled="true" focusable="false" focused="false"
                                                                  scrollable="false" long-clickable="false"
                                                                  password="false" selected="false"
                                                                  bounds="[36,749][108,821]"/>
                                                        </node>
                                                        <node index="1" text="" resource-id=""
                                                              class="android.widget.RelativeLayout"
                                                              package="com.android.settings" content-desc=""
                                                              checkable="false" checked="false" clickable="false"
                                                              enabled="true" focusable="false" focused="false"
                                                              scrollable="false" long-clickable="false" password="false"
                                                              selected="false" bounds="[216,676][1032,894]">
                                                            <node index="0" text="Data usage"
                                                                  resource-id="android:id/title"
                                                                  class="android.widget.TextView"
                                                                  package="com.android.settings" content-desc=""
                                                                  checkable="false" checked="false" clickable="false"
                                                                  enabled="true" focusable="false" focused="false"
                                                                  scrollable="false" long-clickable="false"
                                                                  password="false" selected="false"
                                                                  bounds="[216,724][457,789]"/>
                                                            <node index="1" text="5.80 MB of data used"
                                                                  resource-id="android:id/summary"
                                                                  class="android.widget.TextView"
                                                                  package="com.android.settings" content-desc=""
                                                                  checkable="false" checked="false" clickable="false"
                                                                  enabled="true" focusable="false" focused="false"
                                                                  scrollable="false" long-clickable="false"
                                                                  password="false" selected="false"
                                                                  bounds="[216,789][616,846]"/>
                                                        </node>
                                                    </node>
                                                    <node index="3" text="" resource-id=""
                                                          class="android.widget.LinearLayout"
                                                          package="com.android.settings" content-desc=""
                                                          checkable="false" checked="false" clickable="true"
                                                          enabled="true" focusable="true" focused="false"
                                                          scrollable="false" long-clickable="false" password="false"
                                                          selected="false" bounds="[0,894][1080,1055]">
                                                        <node index="0" text="" resource-id=""
                                                              class="android.widget.LinearLayout"
                                                              package="com.android.settings" content-desc=""
                                                              checkable="false" checked="false" clickable="false"
                                                              enabled="true" focusable="false" focused="false"
                                                              scrollable="false" long-clickable="false" password="false"
                                                              selected="false" bounds="[0,894][1080,1055]">
                                                            <node index="0" text="" resource-id=""
                                                                  class="android.widget.RelativeLayout"
                                                                  package="com.android.settings" content-desc=""
                                                                  checkable="false" checked="false" clickable="false"
                                                                  enabled="true" focusable="false" focused="false"
                                                                  scrollable="false" long-clickable="false"
                                                                  password="false" selected="false"
                                                                  bounds="[216,894][1032,1055]">
                                                                <node index="0" text="Mobile plan"
                                                                      resource-id="android:id/title"
                                                                      class="android.widget.TextView"
                                                                      package="com.android.settings" content-desc=""
                                                                      checkable="false" checked="false"
                                                                      clickable="false" enabled="true" focusable="false"
                                                                      focused="false" scrollable="false"
                                                                      long-clickable="false" password="false"
                                                                      selected="false" bounds="[216,942][465,1007]"/>
                                                            </node>
                                                        </node>
                                                    </node>
                                                    <node index="4" text="" resource-id=""
                                                          class="android.widget.LinearLayout"
                                                          package="com.android.settings" content-desc=""
                                                          checkable="false" checked="false" clickable="true"
                                                          enabled="true" focusable="true" focused="false"
                                                          scrollable="false" long-clickable="false" password="false"
                                                          selected="false" bounds="[0,1055][1080,1273]">
                                                        <node index="0" text="" resource-id=""
                                                              class="android.widget.LinearLayout"
                                                              package="com.android.settings" content-desc=""
                                                              checkable="false" checked="false" clickable="false"
                                                              enabled="true" focusable="false" focused="false"
                                                              scrollable="false" long-clickable="false" password="false"
                                                              selected="false" bounds="[0,1055][1080,1273]">
                                                            <node index="0" text=""
                                                                  resource-id="com.android.settings:id/icon_frame"
                                                                  class="android.widget.LinearLayout"
                                                                  package="com.android.settings" content-desc=""
                                                                  checkable="false" checked="false" clickable="false"
                                                                  enabled="true" focusable="false" focused="false"
                                                                  scrollable="false" long-clickable="false"
                                                                  password="false" selected="false"
                                                                  bounds="[36,1116][216,1212]">
                                                                <node index="0" text="" resource-id="android:id/icon"
                                                                      class="android.widget.ImageView"
                                                                      package="com.android.settings" content-desc=""
                                                                      checkable="false" checked="false"
                                                                      clickable="false" enabled="true" focusable="false"
                                                                      focused="false" scrollable="false"
                                                                      long-clickable="false" password="false"
                                                                      selected="false" bounds="[36,1128][108,1200]"/>
                                                            </node>
                                                            <node index="1" text="" resource-id=""
                                                                  class="android.widget.RelativeLayout"
                                                                  package="com.android.settings" content-desc=""
                                                                  checkable="false" checked="false" clickable="false"
                                                                  enabled="true" focusable="false" focused="false"
                                                                  scrollable="false" long-clickable="false"
                                                                  password="false" selected="false"
                                                                  bounds="[216,1055][1032,1273]">
                                                                <node index="0" text="VPN"
                                                                      resource-id="android:id/title"
                                                                      class="android.widget.TextView"
                                                                      package="com.android.settings" content-desc=""
                                                                      checkable="false" checked="false"
                                                                      clickable="false" enabled="true" focusable="false"
                                                                      focused="false" scrollable="false"
                                                                      long-clickable="false" password="false"
                                                                      selected="false" bounds="[216,1103][311,1168]"/>
                                                                <node index="1" text="None"
                                                                      resource-id="android:id/summary"
                                                                      class="android.widget.TextView"
                                                                      package="com.android.settings" content-desc=""
                                                                      checkable="false" checked="false"
                                                                      clickable="false" enabled="true" focusable="false"
                                                                      focused="false" scrollable="false"
                                                                      long-clickable="false" password="false"
                                                                      selected="false" bounds="[216,1168][315,1225]"/>
                                                            </node>
                                                        </node>
                                                    </node>
                                                    <node index="5" text="" resource-id=""
                                                          class="android.widget.LinearLayout"
                                                          package="com.android.settings" content-desc=""
                                                          checkable="false" checked="false" clickable="true"
                                                          enabled="true" focusable="true" focused="false"
                                                          scrollable="false" long-clickable="false" password="false"
                                                          selected="false" bounds="[0,1273][1080,1434]">
                                                        <node index="0" text=""
                                                              resource-id="com.android.settings:id/icon_frame"
                                                              class="android.widget.LinearLayout"
                                                              package="com.android.settings" content-desc=""
                                                              checkable="false" checked="false" clickable="false"
                                                              enabled="true" focusable="false" focused="false"
                                                              scrollable="false" long-clickable="false" password="false"
                                                              selected="false" bounds="[36,1305][216,1401]">
                                                            <node index="0" text="" resource-id="android:id/icon"
                                                                  class="android.widget.ImageView"
                                                                  package="com.android.settings" content-desc=""
                                                                  checkable="false" checked="false" clickable="false"
                                                                  enabled="true" focusable="false" focused="false"
                                                                  scrollable="false" long-clickable="false"
                                                                  password="false" selected="false"
                                                                  bounds="[36,1317][108,1389]"/>
                                                        </node>
                                                        <node index="1" text="" resource-id=""
                                                              class="android.widget.RelativeLayout"
                                                              package="com.android.settings" content-desc=""
                                                              checkable="false" checked="false" clickable="false"
                                                              enabled="true" focusable="false" focused="false"
                                                              scrollable="false" long-clickable="false" password="false"
                                                              selected="false" bounds="[216,1273][844,1434]">
                                                            <node index="0" text="Airplane mode"
                                                                  resource-id="android:id/title"
                                                                  class="android.widget.TextView"
                                                                  package="com.android.settings" content-desc=""
                                                                  checkable="false" checked="false" clickable="false"
                                                                  enabled="true" focusable="false" focused="false"
                                                                  scrollable="false" long-clickable="false"
                                                                  password="false" selected="false"
                                                                  bounds="[216,1321][525,1386]"/>
                                                        </node>
                                                        <node index="2" text="" resource-id="android:id/widget_frame"
                                                              class="android.widget.LinearLayout"
                                                              package="com.android.settings" content-desc=""
                                                              checkable="false" checked="false" clickable="false"
                                                              enabled="true" focusable="false" focused="false"
                                                              scrollable="false" long-clickable="false" password="false"
                                                              selected="false" bounds="[844,1273][1032,1434]">
                                                            <node index="0" text="OFF"
                                                                  resource-id="android:id/switch_widget"
                                                                  class="android.widget.Switch"
                                                                  package="com.android.settings" content-desc=""
                                                                  checkable="true" checked="false" clickable="false"
                                                                  enabled="true" focusable="false" focused="false"
                                                                  scrollable="false" long-clickable="false"
                                                                  password="false" selected="false"
                                                                  bounds="[892,1313][1032,1394]"/>
                                                        </node>
                                                    </node>
                                                </node>
                                            </node>
                                        </node>
                                    </node>
                                </node>
                            </node>
                        </node>
                    </node>
                </node>
            </node>
        </node>
        <node index="1" text="" resource-id="android:id/statusBarBackground" class="android.view.View"
              package="com.android.settings" content-desc="" checkable="false" checked="false" clickable="false"
              enabled="true" focusable="false" focused="false" scrollable="false" long-clickable="false"
              password="false" selected="false" bounds="[0,0][1080,72]"/>
        <node index="2" text="" resource-id="android:id/navigationBarBackground" class="android.view.View"
              package="com.android.settings" content-desc="" checkable="false" checked="false" clickable="false"
              enabled="true" focusable="false" focused="false" scrollable="false" long-clickable="false"
              password="false" selected="false" bounds="[0,0][0,0]"/>
    </node>
</hierarchy>